[
    {
        "id": 1,
        "name": "Наезд на пешехода",
        "safetyLevel": 3,
        "coordinates": [
            [76.957902, 43.262843]
        ]
    },
    {
        "id": 2,
        "name": "Столкновение",
        "safetyLevel": 4,
        "coordinates": [
            [76.929725, 43.262828]
        ]
    },
    {
        "id": 3,
        "name": "Столкновение c автобусом",
        "safetyLevel": 3,
        "coordinates": [
            [76.950870, 43.264319]
        ]
    },
    {
        "id": 4,
        "name": "Наезд на велосипедиста",
        "safetyLevel": 4,
        "coordinates": [
            [76.950230, 43.269626]
        ]
    }
]